{
 "absolute_value": 0,
 "align_labels_right": 0,
 "creation": "2025-07-15 23:19:29.426142",
 "custom_format": 1,
 "default_print_language": "en",
 "disabled": 0,
 "doc_type": "Booking",
 "docstatus": 0,
 "doctype": "Print Format",
 "font_size": 14,
 "html": "<div style=\"max-width: 600px; margin: auto; font-family: Arial, sans-serif; border: 1px solid #ddd; padding: 20px;\">\r\n\r\n  <h2 style=\"text-align: center; margin-bottom: 20px;\">\ud83c\udfac Movie Ticket</h2>\r\n\r\n  <table style=\"width: 100%; margin-bottom: 20px;\">\r\n    <tr>\r\n      <td><strong>Booking ID:</strong></td>\r\n      <td>{{ doc.name }}</td>\r\n    </tr>\r\n    <tr>\r\n      <td><strong>Customer:</strong></td>\r\n      <td>{{ doc.customer }}</td>\r\n    </tr>\r\n    <tr>\r\n      <td><strong>Showtime:</strong></td>\r\n      <td>{{ frappe.get_value(\"Showtime\", doc.showtime, \"movie\") }} -\r\n          {{ frappe.get_value(\"Showtime\", doc.showtime, \"show_date\") }}\r\n          {{ frappe.get_value(\"Showtime\", doc.showtime, \"show_time\") }}\r\n      </td>\r\n    </tr>\r\n    <tr>\r\n      <td><strong>Seats:</strong></td>\r\n      <td>{{ doc.seat_numbers }}</td>\r\n    </tr>\r\n    <tr>\r\n      <td><strong>Total Price:</strong></td>\r\n      <td>\u20b9 {{ doc.total_price or \"0.00\" }}</td>\r\n    </tr>\r\n  </table>\r\n\r\n  <div style=\"text-align: center; margin: 30px 0;\">\r\n    <img src=\"{{ doc.qr_image }}\" alt=\"QR Code\" style=\"width: 150px; height: 150px;\">\r\n    <p style=\"font-size: 12px; color: #666;\">Scan QR at theatre entrance</p>\r\n  </div>\r\n\r\n  <hr style=\"margin: 30px 0;\">\r\n\r\n  <div style=\"font-size: 12px; color: #555;\">\r\n    <strong>Terms & Conditions:</strong>\r\n    <ul style=\"padding-left: 18px;\">\r\n      <li>Tickets are non-refundable once booked.</li>\r\n      <li>Please carry a valid ID proof along with this e-ticket.</li>\r\n      <li>Entry is allowed up to 10 minutes after showtime.</li>\r\n      <li>Ensure the QR code is visible for scanning.</li>\r\n    </ul>\r\n  </div>\r\n\r\n</div>\r\n",
 "idx": 0,
 "line_breaks": 0,
 "margin_bottom": 15.0,
 "margin_left": 15.0,
 "margin_right": 15.0,
 "margin_top": 15.0,
 "modified": "2025-07-15 23:19:29.426142",
 "modified_by": "Administrator",
 "module": "Cinema",
 "name": "Booking Format",
 "owner": "Administrator",
 "page_number": "Hide",
 "pdf_generator": "wkhtmltopdf",
 "print_format_builder": 0,
 "print_format_builder_beta": 0,
 "print_format_type": "Jinja",
 "raw_printing": 0,
 "show_section_headings": 0,
 "standard": "Yes"
}